LICENSE
MANIFEST.in
README.rst
VERSION
requirements.txt
setup.py
src/appconf_node/__init__.py
src/appconf_node/app.py
src/appconf_node/cli.py
src/appconf_node/jwtlib.py
src/appconf_node/routes.py
src/appconf_node/wsgi.py
src/appconf_node.egg-info/PKG-INFO
src/appconf_node.egg-info/SOURCES.txt
src/appconf_node.egg-info/dependency_links.txt
src/appconf_node.egg-info/entry_points.txt
src/appconf_node.egg-info/requires.txt
src/appconf_node.egg-info/top_level.txt
src/appconf_node/core/__init__.py
src/appconf_node/core/config.py
src/appconf_node/core/serialize.py
src/appconf_node/core/util.py
src/appconf_node/core/validate.py
src/appconf_node/core/api/__init__.py
src/appconf_node/core/api/endpoint.py
src/appconf_node/core/api/resource.py
src/appconf_node/core/api/util.py
src/appconf_node/nginx/__init__.py
src/appconf_node/nginx/models.py
src/appconf_node/nginx/resource.py
src/appconf_node/nginx/util.py
src/appconf_node/run/config.yaml
src/appconf_node/static/3rdpartylicenses.txt
src/appconf_node/static/favicon.ico
src/appconf_node/static/fontawesome-webfont.674f50d287a8c48dc19b.eot
src/appconf_node/static/fontawesome-webfont.912ec66d7572ff821749.svg
src/appconf_node/static/fontawesome-webfont.af7ae505a9eed503f8b8.woff2
src/appconf_node/static/fontawesome-webfont.b06871f281fee6b241d6.ttf
src/appconf_node/static/fontawesome-webfont.fee66e712a8a08eef580.woff
src/appconf_node/static/index.html
src/appconf_node/static/main.8bf677da5520ac706f33.js
src/appconf_node/static/polyfills.2f4a59095805af02bd79.js
src/appconf_node/static/runtime.183b82f2b3a69ecd7ea0.js
src/appconf_node/static/styles.0523c305c25e52597a90.css
src/appconf_node/users/__init__.py
src/appconf_node/users/auth.py
src/appconf_node/users/models.py
src/appconf_node/users/resource.py