Metadata-Version: 1.1
Name: appconf-node
Version: 0.0.9
Summary: Manage a single bare-metal node
Home-page: https://github.com/novopl/appconf-node
Author: Mateusz 'novo' Klos
Author-email: novopl@gmail.com
License: MIT
Platform: UNKNOWN
Classifier: Development Status :: 2 - Pre-Alpha
Classifier: Topic :: Utilities
Classifier: Programming Language :: Python
Classifier: License :: OSI Approved :: MIT License
